[
{"isbn":"9784040652467","title":"レディローズは平民になりたい　１","volume":"","series":"","publisher":"ＫＡＤＯＫＡＷＡ","pubdate":"2018-12-05","cover":"https://cover.openbd.jp/9784040652467.jpg","author":"こおりあめ／原著 ひだかなみ／企画 木与瀬ゆら／著","description":"転生して目指せ“平民エンド”!?　完璧令嬢のお妃ルート脱出ストーリー！","price":"600","genre":"","target":"一般","format":"コミック","content":"コミックス・劇画"}
,
{"isbn":"9784040652818","title":"アラフォーリーマンのシンデレラ転生","volume":"","series":"","publisher":"ＫＡＤＯＫＡＷＡ","pubdate":"2018-12-05","cover":"https://cover.openbd.jp/9784040652818.jpg","author":"原田まりる／著 森倉円／イラスト","description":"オッサン、美少女アイドルとして人生をやり直す！?","price":"1200","genre":"","target":"一般","format":"単行本","content":"日本文学、小説・物語"}
,
{"isbn":"9784040652825","title":"あなたのドラゴン、差押えます　～アラサー公務員の異世界徴税～","volume":"","series":"","publisher":"ＫＡＤＯＫＡＷＡ","pubdate":"2018-12-05","cover":"https://cover.openbd.jp/9784040652825.jpg","author":"飛野猶／著 ｔｏｉ８／イラスト","description":"県税職員が異世界で税金徴収？　ドラゴンなんて差押えられるかよ！","price":"1200","genre":"","target":"一般","format":"単行本","content":"日本文学、小説・物語"}
,
{"isbn":"9784040653655","title":"映画『カメラを止めるな！』アツアツファンブック 『カメラを止めるな！』を止めるな！熱狂のポンデミック","volume":"","series":"","publisher":"ＫＡＤＯＫＡＷＡ","pubdate":"2018-12-05","cover":"https://cover.openbd.jp/9784040653655.jpg","author":"チーム『カメ止め！』感染者／編集","description":"アツアツのポンデミック、ダサかっけ！感染者のみなさん、よろしくで～す","price":"1500","genre":"","target":"一般","format":"単行本","content":"演劇・映画"}
,
{"isbn":"9784040654058","title":"悪役令嬢は、庶民に嫁ぎたい!!　２","volume":"","series":"","publisher":"ＫＡＤＯＫＡＷＡ","pubdate":"2018-12-05","cover":"https://cover.openbd.jp/9784040654058.jpg","author":"なびこ／著 杏亭リコ／原著 封宝／企画","description":"非攻略対象の推しキャラに大接近!? 転生ドタバタラブコメディ、第２弾！","price":"600","genre":"","target":"一般","format":"コミック","content":"コミックス・劇画"}
,
{"isbn":"9784041073469","title":"水曜日郵便局 うーこのてがみ","volume":"","series":"","publisher":"ＫＡＤＯＫＡＷＡ","pubdate":"2018-12-05","cover":"https://cover.openbd.jp/9784041073469.jpg","author":"小池アミイゴ／著・イラスト","description":"ある水曜日のお話です。うーこさんはうーたくんにお手紙を出しました。","price":"1300","genre":"","target":"児童","format":"絵本","content":"日本文学、小説・物語"}
,
{"isbn":"9784047333697","title":"ファイナルファンタジーXI　皆川史生イラストレーションズ","volume":"","series":"","publisher":"Ｇｚブレイン","pubdate":"2018-12-05","cover":"https://cover.openbd.jp/9784047333697.jpg","author":"皆川史生／イラスト","description":"皆川史生、初の『ファイナルファンタジーXI』画集が登場！","price":"3900","genre":"","target":"一般","format":"単行本","content":"諸芸・娯楽"}
,
{"isbn":"9784065132098","title":"炎の姫と戦国の魔女","volume":"","series":"","publisher":"講談社","pubdate":"2018-12-05","cover":"https://cover.openbd.jp/9784065132098.jpg","author":"中村ふみ／著 アオジマイコ／著","description":"戦国時代。赤髪の少女・千寿は、新型鉄砲を手に母の仇討ちのため京へ向かう。道中、出羽大名の娘・晴姫と行動を共にすること……。","price":"690","genre":"","target":"一般","format":"文庫","content":"日本文学、小説・物語"}
,
{"isbn":"9784065139073","title":"昨日のぼくのパーツ","volume":"","series":"","publisher":"講談社","pubdate":"2018-12-05","cover":"https://cover.openbd.jp/9784065139073.jpg","author":"吉野万理子／著","description":"「昨日のパーツ」＝うんこやおしっこ、について真正面から考えてみよう！　小６年の大志は「昨日のぼくのパーツ研究会をたちあげる。","price":"1400","genre":"","target":"児童","format":"単行本","content":"日本文学、小説・物語"}
,
{"isbn":"9784065139455","title":"アラビアン・ウエディング　～灼鷹王の花嫁～","volume":"","series":"","publisher":"講談社","pubdate":"2018-12-05","cover":"https://cover.openbd.jp/9784065139455.jpg","author":"ゆりの菜櫻／著 兼守美行／著","description":"男なのにわけあって王女として育てられた晴希は、政略結婚でデルアン王国に嫁ぐことに。結婚相手の王子はなんと親友のアルディーンで","price":"690","genre":"","target":"一般","format":"文庫","content":"日本文学、小説・物語"}
,
{"isbn":"9784065139622","title":"月と太陽の巡航　欧州妖異譚20","volume":"","series":"","publisher":"講談社","pubdate":"2018-12-05","cover":"https://cover.openbd.jp/9784065139622.jpg","author":"篠原美季／著 かわい千草／著・イラスト","description":"天上の宝石が地上に落ちた？","price":"690","genre":"","target":"一般","format":"文庫","content":"日本文学、小説・物語"}
,
{"isbn":"9784065143773","title":"婦人画報　2019年1月号　×　水布人舎　フェイスタオル＆ウォッシュタオル　特別セット","volume":"","series":"","publisher":"ハースト婦人画報社","pubdate":"2018-12-05","cover":"https://cover.openbd.jp/9784065143773.jpg","author":"ハースト婦人画報社／編集","description":"婦人画報　２０１９年１月号　×　水布人舎　フェイスタオル＆ハンドタオル　特別セット","price":"2500","genre":"","target":"一般","format":"ムック・その他","content":"諸芸・娯楽"}
,
{"isbn":"9784087711707","title":"芙蓉の干城","volume":"","series":"","publisher":"集英社","pubdate":"2018-12-05","cover":"https://cover.openbd.jp/9784087711707.jpg","author":"松井今朝子／著","description":"昭和八年、東京。\n江戸歌舞伎の大作者、三代目桜木治助の孫でありながら現在は早稲田大学に奉職する桜木治郎は、その知識と確かな審美眼で歌舞伎役者や裏方から厚い信頼を集めていた。\n四月。築地小劇場で女優となった親戚の娘・澪子の行く末を案じる実家からの懇願により、木挽座で陸軍軍人・磯田との見合いの席が設けられる。舞台では歌舞伎界の「女帝」荻野沢之丞が見事に舞う中、澪子は真向いの席の男女に、ある違和感を抱いた。\n翌日、木挽座そばで男女の惨殺死体が発見される。遺体は右翼結社「征西会」大幹部・小宮山正憲と芸妓の照世美だった。二人が最後に目撃された木挽座を捜索するため、治郎は警察から協力を要請され、事件に巻き込まれていく。\n澪子もまた、自身が目撃した二人の奇妙な様子を治郎と磯田に打ちけ、それぞれの立場から事件の真相に迫っていくことに――。\n戦争へと歴史の歯車が大きく動いた昭和八年を鮮烈に描き出す、圧巻の歌舞伎ミステリー!\n\n【著者略歴】\n松井今朝子 まつい・けさこ\n1953年京都市生まれ。早稲田大学大学院文学研究科演劇学修士課程修了。\n歌舞伎の企画制作に携わった後、故・武智鉄二氏に師事し、歌舞伎の脚色・演出を手掛ける。\n1997年『東洲しゃらくさし』で小説デビュー。同年『仲蔵狂乱』で時代小説大賞、2007年『吉原手引き草』で直木賞を受賞。\n『師父の遺言』『縁は異なもの 麹町常楽庵 月並の記』『料理通異聞』など著書多数。","price":"1650","genre":"","target":"一般","format":"単行本","content":"日本文学、小説・物語"}
,
{"isbn":"9784087711721","title":"われは歌えどもやぶれかぶれ","volume":"","series":"","publisher":"集英社","pubdate":"2018-12-05","cover":"https://cover.openbd.jp/9784087711721.jpg","author":"椎名誠／著","description":"〈このタイトルは室生犀星が「純文学誌」に書いた小説をぼくが高校生のときに授業中に読んでいて\n──小便がでなくて苦悩するこの小説に首をかしげていたものだ。\n尿が出ない苦悩、なんて高校生には意味がわからなかった。\n今は前立腺肥大によるものと理解できる。\nそのときの犀星は七十二歳でいまのぼくがそれと同だ〉(本文より)\n\n老いてもなお椎名誠! なめんなよな。\n極悪ピロリ菌掃討作戦を決行するも、思いもかけぬ困難が待ち受けたり、\n昔の旅のアレコレも「もう二度と行かないだろう」という苦い述懐になったり。\nシーナさんの日常と非日常。最新エッセイ集。","price":"1400","genre":"","target":"一般","format":"単行本","content":"日本文学、評論、随筆、その他"}
,
{"isbn":"9784087880038","title":"健康マニア、何が楽しい 体にいいことばかりやってて疲れない?","volume":"","series":"","publisher":"集英社","pubdate":"2018-12-05","cover":"https://cover.openbd.jp/9784087880038.jpg","author":"新見正則／著","description":"「不要の我慢はするべきではないのです」。西洋医学と漢方を極めたイグ・ノーベル賞受賞医師が教える゛健康力″のあがる生き方。人生100年時代、たとえ長生きしたって、頭も体も健康でなければ意味はなし。巷にはびこる健康法に振り回される&#12317;健康マニア″たちの目を覚まさせる、ボケずに幸せに長生きするための指南書。好きな食べ物もタバコも酒も我慢して、健康リスクにばかり気を使って暮らして本当に幸せですか? 人はどうせいつか死ぬのだから、目指すのは&#12317;心身ともに死ぬまで現役″。医療と健康のプラットフォーム屋(Medical Platfomer)を名乗る名医が教える目からウロコの新・健康術がここに。\n\n第1章 日常・健康・環境編\n●健康志向反対●人生は楽しんだ人が勝者。長生きした人ではない●タバコばかりを悪者にするのはフェアじゃない●ハッピーに生きるためにはレジリエンスが大切 ●空腹は我慢したほうがいい。でも過剰な我慢は不要●心配性の人はテレビ健康番組を見るな●古くからの教訓は「人間のビッグデータ」。間違っていない●基準値から少々はみ出しても問題ないことが多い●日本のBMI値には悪意が潜んでいる●デブは二種類。健康デブと病的デブ●血圧は上よりも下を、そして脈拍を気にするべし●コレステロール値は無視してもいい●資本主義社会の健康情報なんて信じるのが馬鹿●自分の垢こそ一番の防御機能●現代人が糖質過多であることは間違いない●運動嫌いな人が無理にやってもいいことなんて何もない●免疫力という言葉には要注意●更年期障害を悲観するな\n\n第2章 病気・薬・治療編\n●ストレスががんを誘発しているというのは真実●症状がないがんなら手術を受けるな●転移する前のがんは本当の意味でがんではない●うつ病の多くは寝ていれば治る●症状に慣れるのもひとつの方法薬●どんな病気も死ねば治る\n\n第3章 老い・認知症・お迎え編\n●長生きの秘訣をすぐ答えられる人は元気な人●肺炎は老人の友?●認知症予防には仲間と一緒にアウトプット●家族のことがわからなくなったらお迎えのとき●「できる限りのことをして」とってはいけない●本好きはボケに要注意\n\n第4章 医者・医療・漢方編\n●現代医療はグレーゾーンが相当広い ●医療は運と縁●医者の仕事は人生充実アドバイザー●効果の相関が漢方の歴史●漢方が西洋医学の中に溶けこむことが理想  \n\n●プロフィール\n'59年生まれ。医学博士。慶應義塾大学医学部卒業、オックスフォード大学医学部博士課程留学。移植免疫学でDoctor of Philosophy(DPhil)取得。現・帝京大医学部外科准教授。愛誠病院漢方外来統括医師。アメリカ外科学会フェロー(FACS)、日本外科学会専門医・指導医。日本東洋医学会専門医・指導医、日本脈管学会専門医など。外科医で漢方医でもあり、イグ・ノーベル賞を受賞したサイエンティスト、健康と医療のプラットフォーム屋(Medical Platfomer)と","price":"1300","genre":"","target":"一般","format":"単行本","content":"日本文学、評論、随筆、その他"}
,
{"isbn":"9784092812390","title":"妖怪ウォッチ4コマだじゃれクラブ","volume":"","series":"","publisher":"小学館","pubdate":"2018-12-05","cover":"https://cover.openbd.jp/9784092812390.jpg","author":"レベルファイブ／監修・原著 春風邪三太／イラスト 利田浩一／著 古城宏／編集","description":"妖怪だじゃれで笑っちゃおう！ \n\n 劇場版アニメ「妖怪ウォッチ フォーエバーフレンズ」や、アニメ「妖怪ウォッチシャドウサイド」、またニンテンドースイッ「妖怪ウォッチ4」にも登場する妖怪たちがだじゃれ4コマになって大集合！ オールカラーで約100本の超ボリューム！","price":"833","genre":"","target":"児童","format":"図鑑","content":"諸芸・娯楽"}
,
{"isbn":"9784094063738","title":"もつれ","volume":"","series":"","publisher":"小学館","pubdate":"2018-12-05","cover":"https://cover.openbd.jp/9784094063738.jpg","author":"ジグムントミウォシェフスキ／著 田口俊樹／翻訳","description":"予想の斜め上を行くポーランドの怪作小説！ \n\n  ワルシャワ市内の教会で、右眼に焼き串を突かれた男の遺体が見つかった。被害者は、娘を自殺で亡くした印刷会社経営者。容疑者は、彼と共にグループセラピーに参加していた男女3人と、主催者のセラピスト。中年検察官シャツキは早速捜査を進めるが、調べれば調べるほど事件の闇は深まっていく。一方で、愛する妻と娘に恵まれながらもどこか閉塞感を抱いていたシャツキは、事件の取材に訪れた若い女性記者に惹かれ、罪悪感と欲望との狭間で悶々とする。やがて、被害者の遺品から過去のある事件に気づくシャツキ。真実に手が届こうとしたその時、思わぬ事態が……。\n 日本中のミステリーファンを唸らせたポーランドの怪作『怒り』、その「シャツキ三部作」の第一作がいよいよ日本上陸。ハードボイルドなのにポップ、凄惨なのに笑える、一度読んだら中年クライシス男のボヤキがやみつきに!? 予想の斜め上を行く傑作ミステリー！","price":"970","genre":"","target":"一般","format":"文庫","content":"外国文学小説"}
,
{"isbn":"9784094065817","title":"冥土ごはん 洋食店 幽明軒","volume":"","series":"","publisher":"小学館","pubdate":"2018-12-05","cover":"https://cover.openbd.jp/9784094065817.jpg","author":"伽古屋圭市／著","description":"死者の無念は食べて解決。洋食異界ミステリ \n\n  匂いに誘われて入った「洋食店 幽明軒」で、無職の和泉沢悠人はアルバイトを始めることになった。厨房で働くのはシェフの九原脩平と妻・香子、フロアは娘の果菜子が担当している。悠人は果菜子に教わりながらバイト初日の仕事をスタートさせた。無事に営業を終えた午後8時、急に店内の温度が下がり、ドアからゆらりと現れたのは幽霊？ 幽明軒は、現世に思いを残した死者が訪れる洋食店だった。\n 死者たちは、好きな洋食を一品オーダーし、それを食べることで過去のわだかまりを解消することができるという。悠人が初めて接客したのは、大正時代に交通事故で無くなった珠代だった。オーダーはライスオムレツ。結婚を誓い合った恋人と食べる予定のまま、些細なすれ違いから食べることの出来ないまま死んだ。シェフの脩平は珠代の話を聞きながら、恋人の本当の気持ちを導き出す（第1話「別れのオムライス」）。\n「ナポリタンに込めた息子の気持ちとは」「私は誰に殺されたのか」死者たちが遺した思いに寄り添う“幽冥と顕世のはざまの”洋食店での人間模様を描く、全5話収録の食×異界ミステリー！ \n\n 【編集担当からのおすすめ情報】 \n 『鴨川食堂』など、\n美味しいミステリーがお好きな方に、\nぜひ読んでいただきたいミステリーです。\nお腹も心も温まります。","price":"580","genre":"","target":"一般","format":"文庫","content":"日本文学、小説・物語"}
,
{"isbn":"9784094065862","title":"野村の遺言","volume":"","series":"","publisher":"小学館","pubdate":"2018-12-05","cover":"https://cover.openbd.jp/9784094065862.jpg","author":"野村克也／著","description":"野村野球の真髄、最初で最後の本格捕手論 \n\n 「キャッチャーは試合の脚本家。脚本がだめではいい作品は生まれない」と、名捕手不在のいまのプロ野球を憂う著者が、「これけは言いのこしておきたい」ことは何なのか。\n真のプロフェッショナルを知る著者が、これこそ捕手の醍醐味と言われる「配球」と「駆け引き」について、知られざるエピソードと勝負の法則、名捕手の条件を語り尽くす。\n\n文庫版スペシャル「野村克也×山崎武司のぼやき＆言いたい放題対談」を特別収録！ \n","price":"690","genre":"","target":"一般","format":"文庫","content":"日本文学、評論、随筆、その他"}
,
{"isbn":"9784094065879","title":"戻る男","volume":"","series":"","publisher":"小学館","pubdate":"2018-12-05","cover":"https://cover.openbd.jp/9784094065879.jpg","author":"山本甲士／著","description":"過去をリセットできるとしたらどうしますか \n\n  ある日、作家の新居航生のもとに一通の書状が届いた。航生は、作家として5年前に出版した『もう一つの扉』が大ヒットを飛ばしたが、その後は小説を書いておらず、離婚して一人暮らしをしていた。書状は、タイムスリップを研究しているという、八木俊太郎という人物からだった。それによれば、ある程度ならタイムスリップが可能だという。可能なのは、過去へのタイムスリップのみで、未来は不可能。その過去も、当人が生きている時代に限られ、過去の自分自身に会えるわけではなく、当時の自分に重なることになる。そして、歴史を大きく変えるようなことを実行するのは不可能、ということだった。\n 自分が体験した小さな事実なら変えられる―。 考えた末に、実際に体験したことを雑誌に書くことにして、航生は八木の提案を受け入れタイムスリップを経験してみることにした。\n 航生は、中学生のときにいじめの標的にされたことがあり、航生は、この過去を変えようと思った。八木の運転で連れて行かれた部屋で八木と話すうちに、航生は、中二の文化祭会場である市民会館のホールの席に学生服を着て座っていた――。果たして、過去はリセットできるのか。\n","price":"650","genre":"","target":"一般","format":"文庫","content":"日本文学、小説・物語"}
,
{"isbn":"9784094065893","title":"小説源氏物語 STORY OF UJI","volume":"","series":"","publisher":"小学館","pubdate":"2018-12-05","cover":"https://cover.openbd.jp/9784094065893.jpg","author":"林真理子／著","description":"古典文学の名作を林真理子が官能的に再構築 \n\n  誠実だが真面目で性に対しても淡泊な薫と、好色で不誠実だが女性に優しく情熱的な匂宮。光源氏の血をひく、二人のイケメン貴公子が都から離れた、美しい水郷の地＝宇治で繰り広げる恋愛ゲーム。裏切り、嫉妬、懐疑･･･。そしてふたりの間で翻弄される女、浮舟の揺れ動く心と、愛欲におぼれゆく様を、恋愛小説の名手、林真理子がリアルに、執拗に、そして官能的に描き切った問題作。\n 平安の恋愛小説の原初として、千年以上にわたって読み継がれてきた｢源氏物語｣の中でも、人気の宇治十帖｣部分を大胆に新解釈。世紀を超えた二股愛の末に、浮舟が向かった衝撃的末路は!? \n 美しい情景描写と、濃密にしてエロティックな性愛表現。さらにはスピード感溢れる展開に読み始めたら止まらない！ 果たしてこれは古典文学なのか、それとも現代小説なのか？ \n前作「六条御息所 源氏がたり」（上下巻）に続く、林真理子版｢小説源氏物語｣の、いよいよ完結編です！ \n\n 【編集担当からのおすすめ情報】 \n 表紙装画には、日本を代表する日本画家、千住博の「源氏物語 宿木」を使用。解説はエッセイスト酒井順子。ほぼ同時期に発売される和樂本誌では、本作の見所を、林真理子氏自らが解説。日本の文壇を代表する作家と、日本画壇のトップが取り組んだ、21世紀の「源氏物語」。j古典文学や平安文化に関心がなくても、現代小説を読むように、恋愛ドラマをみるように楽しめる、超官能的平安エンタメ恋愛小説!","price":"670","genre":"","target":"一般","format":"文庫","content":"日本文学、小説・物語"}
,
{"isbn":"9784094065909","title":"シンプル・カオス","volume":"","series":"","publisher":"小学館","pubdate":"2018-12-05","cover":"https://cover.openbd.jp/9784094065909.jpg","author":"ごとうしのぶ／著 吉野花／イラスト","description":"彼と僕の関係が変わる――日常の非日常。 \n\n ある夏の日のこと。高校生の鏑木摂は親友の名和秀真に告白し、見事玉砕してしまう。直後、暑さに倒れた摂は保健室で目覚めたが、そこはすでに「今までいた世界とそっくりなのにまるで違う世界」に変わってしまっていた。\n周囲の人々との関係も以前とは違う。いるはずのない人が存在している。これが夢でないのなら、自分は何かのはずみで別の世界へ移動したんだ――そう考えた摂を、「こちらの世界」の秀真は祖父が管理する水神社へ連れていく。どうやら彼は、この不思議な入れ替わりの事情を知っているようで……？ 新感覚パラレル・ストーリー！","price":"580","genre":"","target":"一般","format":"文庫","content":"日本文学、小説・物語"}
,
{"isbn":"9784094065916","title":"えんま様の忙しい49日間 散り桜の頃","volume":"","series":"","publisher":"小学館","pubdate":"2018-12-05","cover":"https://cover.openbd.jp/9784094065916.jpg","author":"霜月りつ／著 スオウ／イラスト","description":"吉祥寺に住む閻魔様が現世の事件を解決！ \n\n 吉祥寺の古アパートに住む青年・大央炎真の正体は、地獄の大王閻魔様。久しぶの休暇を現世でのんびり過ごそうと、地獄から百年ぶりの現代日本にやってきた炎真だが、アパートの大家でもある腹黒な地蔵菩薩が差し出す美味しそうなスイーツに釣られて、はぐれ霊を彼岸に送ったり、罪を犯す生者を懲らしめたり……と、つい真面目に労働しては後悔する毎日だ。\n ある日、焼き鳥をつまみながら散りかけた桜の見物でもしようと井の頭公園にやってきた炎真は、赤ん坊を抱えた着物姿の美女と出会う。公園の池に祀られている弁財天だと名乗る彼女は、「池の主が天に昇るのを助けてほしい」と炎真に頼み込むが……。\n 池の主と赤子をめぐる不思議な一夜、結婚をひかえた姉が見る悪夢の結末、悪徳ブリーダーに立ち向かう少年の奮闘など、痛快＆感動の五話を収録。\n 「地獄でまた会おう」と言いながら悪を裁き、死者に安らぎを与える炎真と、イケメンホスト風な地獄の秘書官・小野篁、記録係のお子ちゃま・司録＆司命ら、賑やかな仲間が大活躍。地獄行き事件解決録、第二弾です！\n","price":"580","genre":"","target":"一般","format":"文庫","content":"日本文学、小説・物語"}
,
{"isbn":"9784097268338","title":"トロールズ さがして！みつけて！","volume":"","series":"","publisher":"小学館","pubdate":"2018-12-05","cover":"https://cover.openbd.jp/9784097268338.jpg","author":"ユニバーサル／監修","description":"トロールズの世界でさがしっこを楽しむ絵本 \n\n 2018年10月からテレビ東京他でテレビ大人気放送中の、ドリームワークス制作のアニメーション「トロールズ」のキャラクターやグッズをシーンの中から探して遊ぶ、カラフルでかわいい、さがして！みつけて！翻訳絵本です。妖精のトロールズやかわいいグッズなど、1001個ものさがしっこ遊びが楽しめます。\n","price":"950","genre":"","target":"児童","format":"絵本","content":"絵画・彫刻"}
,
{"isbn":"9784097268345","title":"ジュラシック・ワールド さがして！みつけて！","volume":"","series":"","publisher":"小学館","pubdate":"2018-12-05","cover":"https://cover.openbd.jp/9784097268345.jpg","author":"ユニバーサル／監修","description":"映画の名場面から恐竜たちを探して遊ぶ絵本 \n\n 大ヒット映画「ジュラシック・ワールド」の世界をテーマにした、さがして！みつけて！翻訳絵本です。人気の恐竜たちやグッズなどを、映画のダイジェストシーンの中から探して、楽しく遊ぶ絵本です。","price":"900","genre":"","target":"児童","format":"絵本","content":"絵画・彫刻"}
,
{"isbn":"9784099430344","title":"松本零士 不滅のアレグレット〈完全版〉","volume":"","series":"","publisher":"小学館","pubdate":"2018-12-05","cover":"https://cover.openbd.jp/9784099430344.jpg","author":"松本零士／著","description":"入手困難だった幻の名作が完全版で甦る！ \n\n かつてFM誌『FMレコパル』に連載されていた「ライブコミック」から、松本零士氏の作品のみを集めた単行本『不滅のアレグレット』（1979年刊行）。カラヤン、フルトベングラーといった名指揮者やクライスラーなどの名演奏家たちの生き様を松本零士氏ならではの独特の世界観のなかで描いたこの作品集は、ファンの間でその存在が語り継がれながらも久しく手に入らなかった知られざる名作。この単行本に、未収録作品9点（単行本刊行以前4点、刊行以後5点）を加え、作品で言及されているクラシックの名曲を収めたCDを同梱した豪華完全版を松本零士氏80周年記念として刊行。未収録作品は「大悲愴序曲 チャイコフスキー」「消えない惑星～ホルスト～」など。バンドルされるCDはドイツ・グラモフォンなどの名門クラシックレーベルを持つユニバーサル・ミュージックの音源を使用。表題のベートーベン交響曲第7番第2楽章『不滅のアレグレット』（フルトベングラー＆ベルリン・フィル）を始め、ホルスト組曲『惑星』（カラヤン＆ウィーン・フィル）などの名曲が並ぶ。松本零士氏ファンはもちろん、コミックでわかるクラシック入門本としても楽しめる絶好の1冊！ \n\n 【編集担当からのおすすめ情報】 \n 1979年版の単行本『不滅のアレグレット』に収録されなかった9点の作品は、今ではどれも極めて入手が難しいレアな作品ばかり。ようやく今回、完全版として松本零士氏のクラシック作品を一気に読むことができるようになりました。今まであまり多く語られることのなかったクラシック音楽との関わりについては巻頭インタビューでじっくり紹介していますのでこちらにも注目してください。松本零士ファン必携の一冊です！","price":"2800","genre":"","target":"一般","format":"磁性媒体など","content":"コミックス・劇画"}
,
{"isbn":"9784150019389","title":"ブルーバード、ブルーバード","volume":"","series":"","publisher":"早川書房","pubdate":"2018-12-05","cover":"https://cover.openbd.jp/9784150019389.jpg","author":"アッティカ・ロック／著 高山真由美／翻訳","description":"ハイウェイ沿いの田舎町で白人女性と黒人男性の死体が発見される。人種差別が根深く絡む事件に、黒人のテキサス・レンジャーが捜査に乗り出すが──。その衝撃的な内容が高く評価され、米書評界で絶賛された話題のアメリカ探偵作家クラブ賞最優秀長篇賞受賞作","price":"1800","genre":"","target":"一般","format":"新書","content":"外国文学小説"}
,
{"isbn":"9784150122089","title":"ヴィシュナ熱","volume":"582","series":"宇宙英雄ローダン・シリーズ","publisher":"早川書房","pubdate":"2018-12-05","cover":"https://cover.openbd.jp/9784150122089.jpg","author":"トーマス・ツィーグラー／著 アルント・エルマー／著 嶋田洋一／翻訳","description":"四次元性の影チュトンがヴィシュナ第五の災い&quot;愛&quot;がくると告げる。困惑するブルらの前に、宇宙から無数の異生命体が降下した！","price":"680","genre":"","target":"一般","format":"文庫","content":"外国文学小説"}
,
{"isbn":"9784150122102","title":"星間帝国の皇女－ラスト・エンペロー－","volume":"","series":"","publisher":"早川書房","pubdate":"2018-12-05","cover":"https://cover.openbd.jp/9784150122102.jpg","author":"ジョン・スコルジー／著 内田昌之／翻訳","description":"星系間交易の礎&quot;フロー&quot;が崩壊か!?　思いがけず皇帝の後継者となったカーデニアは、いきなり帝国最大の危機に直面する羽目に！","price":"1160","genre":"","target":"一般","format":"文庫","content":"外国文学小説"}
,
{"isbn":"9784150313524","title":"ｒｅｖｉｓｉｏｎｓ　リヴィジョンズ １","volume":"","series":"","publisher":"早川書房","pubdate":"2018-12-05","cover":"https://cover.openbd.jp/9784150313524.jpg","author":"木村航／著 Ｓ・Ｆ・Ｓ／著","description":"渋谷中心部が突如三百年先の未来に跳ばされた。巻き込まれた高校生の大介らは、リヴィジョンズと呼ばれる未来人に遭遇するが……","price":"800","genre":"","target":"一般","format":"文庫","content":"日本文学、小説・物語"}
,
{"isbn":"9784150313531","title":"ｒｅｖｉｓｉｏｎｓ　時間ＳＦアンソロジー","volume":"","series":"","publisher":"早川書房","pubdate":"2018-12-05","cover":"https://cover.openbd.jp/9784150313531.jpg","author":"大森望／編集","description":"Ｃ・Ｌ・ムーアの単行本未収録の名作「ヴィンテージ・シーズン」新訳ほか、驚愕のヴィジョンを提示する古今東西の時間ＳＦ傑作選","price":"820","genre":"","target":"一般","format":"文庫","content":"日本文学、小説・物語"}
,
{"isbn":"9784150505332","title":"モサド 暗躍と抗争の70年史","volume":"","series":"","publisher":"早川書房","pubdate":"2018-12-05","cover":"https://cover.openbd.jp/9784150505332.jpg","author":"小谷賢／著","description":"「導かなければ民は滅びる」。聖書の一句を基に、敵に囲まれたユダヤ国家を陰で支える情報機関の実像とは？　新章を増補した決定版","price":"900","genre":"","target":"一般","format":"文庫","content":"政治-含む国防軍事"}
,
{"isbn":"9784151744075","title":"過ぎ去りし世界","volume":"","series":"","publisher":"早川書房","pubdate":"2018-12-05","cover":"https://cover.openbd.jp/9784151744075.jpg","author":"デニス・ルヘイン／著 加賀山卓朗／翻訳","description":"第二次大戦下のフロリダ。ギャング稼業から足を洗ったジョー・コグリンの命を狙うのは誰なのか？　激動の裏社会を生きる男の物語","price":"1200","genre":"","target":"一般","format":"文庫","content":"外国文学小説"}
,
{"isbn":"9784152098184","title":"大統領失踪 上","volume":"","series":"","publisher":"早川書房","pubdate":"2018-12-05","cover":"https://cover.openbd.jp/9784152098184.jpg","author":"ビル・クリントン／著 ジェイムズ・パタースン／著 越前敏弥／翻訳 久野郁子／翻訳","description":"アメリカ合衆国大統領ダンカンは密かにホワイトハウスを抜け出した。世界を崩壊させかねない大規模サイバーテロを防ぐには他に道はなかったのだ！　ニューヨーク・タイムズ・ベストセラー第１位獲得！　元大統領とベストセラー作家のコンビが放つ傑作スリラー","price":"1800","genre":"","target":"一般","format":"単行本","content":"外国文学小説"}
,
{"isbn":"9784152098191","title":"大統領失踪 下","volume":"","series":"","publisher":"早川書房","pubdate":"2018-12-05","cover":"https://cover.openbd.jp/9784152098191.jpg","author":"ビル・クリントン／著 ジェイムズ・パタースン／著 越前敏弥／翻訳 久野郁子／翻訳","description":"","price":"1800","genre":"","target":"一般","format":"単行本","content":"外国文学小説"}
,
{"isbn":"9784152098207","title":"何があってもおかしくない","volume":"","series":"","publisher":"早川書房","pubdate":"2018-12-05","cover":"https://cover.openbd.jp/9784152098207.jpg","author":"エリザベス・ストラウト／著 小川高義／翻訳","description":"十数年ぶりに帰郷することになった作家ルーシー・バートンとその周囲の人々を描いた短篇九篇を収録。ピュリッツァー賞作家の最新作！","price":"2300","genre":"","target":"一般","format":"単行本","content":"外国文学小説"}
,
{"isbn":"9784152098214","title":"クリエイティブ・スイッチ","volume":"","series":"","publisher":"早川書房","pubdate":"2018-12-05","cover":"https://cover.openbd.jp/9784152098214.jpg","author":"アレン・ガネット／著 千葉敏生／翻訳","description":"ヒット商品を生み出す秘訣は何か？　データ分析のプロが、天才クリエイターたちに取材し、企画を成功させるための思考・行動を語る！","price":"1700","genre":"","target":"一般","format":"単行本","content":"経営"}
,
{"isbn":"9784152098221","title":"ダーティペアの大跳躍","volume":"8","series":"ダーティペア・シリーズ","publisher":"早川書房","pubdate":"2018-12-05","cover":"https://cover.openbd.jp/9784152098221.jpg","author":"高千穂遙／著","description":"犯罪組織の一味を追いつめたユリとケイだったが、奇妙な異世界で想像を絶する大冒険へ。果たして無事に帰れるのか？　ダーティペア！","price":"1400","genre":"","target":"一般","format":"単行本","content":"日本文学、小説・物語"}
,
{"isbn":"9784152098238","title":"黒猫のいない夜のディストピア","volume":"","series":"","publisher":"早川書房","pubdate":"2018-12-05","cover":"https://cover.openbd.jp/9784152098238.jpg","author":"森晶麿／著","description":"ポオの研究を続ける付き人は、街で遭遇した自分そっくりの人影に怯えていた。頼りの黒猫は、些細なことで喧嘩になったまま出張に出て傍にいない。時を同じくして家に届いた不審な絵葉書、次第に怪しくなる母親の言動……付き人の周囲で一体何が起きているのか","price":"1800","genre":"","target":"一般","format":"単行本","content":"日本文学、小説・物語"}
,
{"isbn":"9784267021619","title":"嘉納治五郎","volume":"","series":"","publisher":"潮出版社","pubdate":"2018-12-05","cover":"https://cover.openbd.jp/9784267021619.jpg","author":"真田久／著","description":"日本スポーツ近代化に大きく貢献。ＩＯＣ委員として、近代オリンピックムーブメントの立役者となった嘉納治五郎を徹底解説！","price":"602","genre":"文庫","target":"一般","format":"文庫","content":"伝記"}
,
{"isbn":"9784267021657","title":"２１世紀の宗教改革","volume":"","series":"","publisher":"潮出版社","pubdate":"2018-12-05","cover":"","author":"佐藤優／著","description":"創価学会発展の要因を佐藤優が小説『人間革命』から読み解く！","price":"1200","genre":"哲学・宗教","target":"一般","format":"単行本","content":"日本文学、評論、随筆、その他"}
,
{"isbn":"9784296101597","title":"日経PC21総集編　Windows10 活用大事典","volume":"","series":"日経BPパソコンベストムック","publisher":"日経ＢＰ","pubdate":"2018-12-05","cover":"https://cover.openbd.jp/9784296101597.jpg","author":"日経PC21／編集","description":"基本の設定から究極の裏ワザまで\nWindows 10のすべてがわかる！\n","price":"1600","genre":"","target":"雑誌扱い","format":"ムック・その他","content":"電子通信"}
,
{"isbn":"9784309287072","title":"樹脂粘土でつくるわくわくミニチュアお弁当","volume":"","series":"","publisher":"河出書房新社","pubdate":"2018-12-05","cover":"","author":"関口真優／著","description":"唐揚げや卵焼きの定番弁当、お花見弁当、のり弁、仕出し弁当…お弁当箱まで全部作れます！何度も使うパーツの型取りの方法もご紹介。","price":"1500","genre":"","target":"一般","format":"単行本","content":"家事"}
,
{"isbn":"9784309287102","title":"魔法のデコレーション・メソッド","volume":"","series":"","publisher":"河出書房新社","pubdate":"2018-12-05","cover":"","author":"熊谷裕子／著","description":"お店のような美しいケーキを作るためのメソッドを紹介。フルーツの切り方、絞り口金の使い方一つでいつもと見違える仕上がりに!","price":"1500","genre":"","target":"一般","format":"単行本","content":"家事"}
,
{"isbn":"9784309287119","title":"プティ・ガトーのデコレーション・メソッド","volume":"","series":"","publisher":"河出書房新社","pubdate":"2018-12-05","cover":"","author":"熊谷裕子／著","description":"パティスリーに並んでいる一人分サイズのケーキ。　スポンジ、タルトレット、ムースなど定番＆人気のプティ・ガトーが一冊に！","price":"1500","genre":"","target":"一般","format":"単行本","content":"家事"}
]
