[
{"isbn":"9784065125458","title":"完璧という領域","volume":"","series":"","publisher":"講談社","pubdate":"2019-05-29","cover":"https://cover.openbd.jp/9784065125458.jpg","author":"熊川哲也／著","description":"熊川哲也、２１年ぶりの自伝","price":"1800","genre":"","target":"一般","format":"単行本","content":"音楽・舞踊"}
,
{"isbn":"9784065153826","title":"クッキングパパ　アジフライ","volume":"","series":"","publisher":"講談社","pubdate":"2019-05-29","cover":"https://cover.openbd.jp/9784065153826.jpg","author":"うえやまとち／著","description":"新たな時代の幕開けも、おいしい料理とともに！　愛情に満ちたごちそうがいっぱい！！","price":"333","genre":"","target":"雑誌扱い","format":"コミック","content":"コミックス・劇画"}
,
{"isbn":"9784065154014","title":"moja","volume":"","series":"","publisher":"講談社","pubdate":"2019-05-29","cover":"https://cover.openbd.jp/9784065154014.jpg","author":"吉田桃子／著","description":"主人公は毛深いのが悩みの中二女子。たかが毛、されど毛。悩める乙女の明日はどっち！？悩みを解決するまでをユーモラスに描きます！","price":"1300","genre":"","target":"児童","format":"単行本","content":"日本文学、小説・物語"}
,
{"isbn":"9784065155134","title":"ムーミン全集［新版］2　たのしいムーミン一家","volume":"","series":"","publisher":"講談社","pubdate":"2019-05-29","cover":"","author":"トーベ・ヤンソン／著 山室静／翻訳","description":"５０年以上愛されてきた「ムーミン」の原典、決定版！クリアになったさしえ、読みやすくなった翻訳、おしゃれなカバーが目印！","price":"1500","genre":"","target":"児童","format":"全集・双書","content":"外国文学小説"}
,
{"isbn":"9784065155929","title":"ベストバウト　オブ　はじめの一歩！　幕之内一歩VS．ウォーリー　日本フェザー級10回戦　驚異の野生児編","volume":"","series":"","publisher":"講談社","pubdate":"2019-05-29","cover":"https://cover.openbd.jp/9784065155929.jpg","author":"森川ジョージ／著","description":"＊","price":"648","genre":"","target":"雑誌扱い","format":"コミック","content":"コミックス・劇画"}
,
{"isbn":"9784065156841","title":"ジパング　史実にはない戦史の結末　アンコール刊行","volume":"","series":"","publisher":"講談社","pubdate":"2019-05-29","cover":"https://cover.openbd.jp/9784065156841.jpg","author":"かわぐちかいじ／著","description":"かわぐちかいじが描く、傑作歴史改変ＳＦ！！","price":"630","genre":"","target":"雑誌扱い","format":"コミック","content":"コミックス・劇画"}
,
{"isbn":"9784073408420","title":"よくわかる　海　ルアーの選びかた","volume":"","series":"","publisher":"主婦の友社","pubdate":"2019-05-29","cover":"https://cover.openbd.jp/9784073408420.jpg","author":"ケイエス企画／編集","description":"ルアー釣りを知らない人のための最初の本。使い方を基軸に釣れる魚種や狙う場所が理解できる全て網羅したオールインワン構成。","price":"1280","genre":"","target":"実用","format":"単行本","content":"体育・スポーツ"}
,
{"isbn":"9784074356669","title":"ＤＶＤつき　体が硬い人のヨガ入門　４週間プログラム","volume":"","series":"","publisher":"主婦の友社","pubdate":"2019-05-29","cover":"https://cover.openbd.jp/9784074356669.jpg","author":"ＨＩＫＡＲＵ／著","description":"人気ヨガ講師HIKARUさんによる待望のALL撮りおろしBOOK！初心者や体が硬い人でもおうちでヨガを楽しめます。","price":"1300","genre":"","target":"実用","format":"単行本","content":"家事"}
,
{"isbn":"9784074367375","title":"Ｊａｎｃｈａｎ　Ｓｔｙｌｅ　Ｂｏｏｋ　Ｈｉ　Ｈａａｉ！","volume":"","series":"","publisher":"主婦の友社","pubdate":"2019-05-29","cover":"https://cover.openbd.jp/9784074367375.jpg","author":"Ｊａｎｃｈａｎ／著","description":"BNK48卒業後、日本でソロ活動を開始したJanの日本初のフォトブック。寝起き姿など貴重なプライベート写真が満載の1冊。","price":"1574","genre":"","target":"一般","format":"単行本","content":"写真・工芸"}
,
{"isbn":"9784074384815","title":"完全図解　糖尿病のすべて","volume":"","series":"","publisher":"主婦の友社","pubdate":"2019-05-29","cover":"https://cover.openbd.jp/9784074384815.jpg","author":"片山隆司／監修 貴堂明世／監修 伊藤玲子／監修","description":"高血糖はなぜ怖い？　1000万人とされる糖尿病。基本から薬物療法、運動療法、100の対策レシピ付きですべてがわかる","price":"1400","genre":"","target":"実用","format":"単行本","content":"家事"}
,
{"isbn":"9784093886888","title":"B級キャスター","volume":"","series":"","publisher":"小学館","pubdate":"2019-05-29","cover":"https://cover.openbd.jp/9784093886888.jpg","author":"村尾信尚／著","description":"今、明かす『NEWS ZERO』の舞台裏 \n\n 今を去ること12年前。\n著者は、嫌われ者の財務省出身の元・官僚で、しかも県知事選の落選者だった。そんな著者にまさかの、キャスター就任の依頼が！？\n そこから始まった怒涛の日々。化粧やコンタクトレンズ装着、発声練習に、アクセントの矯正…。とまどいばかりの毎日が始まるも、持ち前の鈍感力と、「日本をよくする」という思いで、駆け抜けていく。\n 『NEWS ZERO』のコンセプトは、「日本をよくする」。\nこれは、番組開始前夜、番組の幹部と著者が何度も語り合って決めたもの。\nこの目標のため、著者は硬いニュースを、わかりやすく伝えようと東奔西走する。著者だけではない。スタッフはもちろん、星野仙一氏や小林麻央氏、櫻井翔氏といった共演するキャスター陣も奮闘する。\nしかし、視聴率を重視せざるを得ないスタッフとの対立も目立ち始めて…。\n 「素人キャスター」だった著者だからこそ語れるNEWS番組の熱き舞台裏。\n「網走一家」」に属していた少年時代や、「悪代官」と呼ばれた官僚時代の知られざる事実も紹介！\n さらに、著者だけが知る、星野仙一氏や、櫻井翔氏、桐谷美玲氏らのエピソードも満載！\n\n \n  \n\n 【編集担当からのおすすめ情報】 \n 発売前にこの本のゲラを読んだ方から、多くの反響をいただきました。\n「村尾さんって、こんなに面白い人だったんだ！」\n「村尾キャスターって、ものすごく熱い人だったんだね！」\n「どのニュース番組も同じような芸能ネタを流す理由がわかった」\n著者の村尾さんは、本当にまっすぐな熱い魂の持ち主です。その村尾さんが、「視聴率ゼロ」と揶揄（やゆ）されながらも、日本を良くしようと努力を続けた奮戦記です。さらに星野仙一さや小林麻央さん、櫻井翔さんの思い出話なども盛り込んだ、読みどころだらけの1冊です。\n\n\n","price":"1400","genre":"","target":"一般","format":"単行本","content":"日本文学、評論、随筆、その他"}
,
{"isbn":"9784101012919","title":"介護殺人 追いつめられた家族の告白","volume":"","series":"新潮文庫","publisher":"新潮社","pubdate":"2019-05-29","cover":"https://cover.openbd.jp/9784101012919.jpg","author":"毎日新聞大阪社会部取材班／著","description":"","price":"550","genre":"文庫","target":"一般","format":"文庫","content":"日本文学、評論、随筆、その他"}
,
{"isbn":"9784101014319","title":"許されようとは思いません","volume":"","series":"新潮文庫","publisher":"新潮社","pubdate":"2019-05-29","cover":"https://cover.openbd.jp/9784101014319.jpg","author":"芦沢央／著","description":"","price":"550","genre":"文庫","target":"一般","format":"文庫","content":"日本文学、小説・物語"}
,
{"isbn":"9784101024042","title":"不良少年とキリスト","volume":"","series":"新潮文庫","publisher":"新潮社","pubdate":"2019-05-29","cover":"https://cover.openbd.jp/9784101024042.jpg","author":"坂口安吾／著","description":"","price":"490","genre":"文庫","target":"一般","format":"文庫","content":"日本文学、評論、随筆、その他"}
,
{"isbn":"9784101134895","title":"五瓣の椿","volume":"","series":"新潮文庫","publisher":"新潮社","pubdate":"2019-05-29","cover":"https://cover.openbd.jp/9784101134895.jpg","author":"山本周五郎／著","description":"","price":"550","genre":"文庫","target":"一般","format":"文庫","content":"日本文学、小説・物語"}
,
{"isbn":"9784101205830","title":"ゆびさきたどり","volume":"","series":"新潮文庫","publisher":"新潮社","pubdate":"2019-05-29","cover":"https://cover.openbd.jp/9784101205830.jpg","author":"花房観音／著","description":"","price":"490","genre":"文庫","target":"一般","format":"文庫","content":"日本文学、小説・物語"}
,
{"isbn":"9784101259475","title":"幻の料亭「百川」ものがたり","volume":"","series":"新潮文庫","publisher":"新潮社","pubdate":"2019-05-29","cover":"https://cover.openbd.jp/9784101259475.jpg","author":"小泉武夫／著","description":"","price":"550","genre":"文庫","target":"一般","format":"文庫","content":"日本文学、評論、随筆、その他"}
,
{"isbn":"9784101321738","title":"籠の鸚鵡","volume":"","series":"新潮文庫","publisher":"新潮社","pubdate":"2019-05-29","cover":"https://cover.openbd.jp/9784101321738.jpg","author":"辻原登／著","description":"","price":"630","genre":"文庫","target":"一般","format":"文庫","content":"日本文学、小説・物語"}
,
{"isbn":"9784101331812","title":"君たちが知っておくべきこと","volume":"","series":"新潮文庫","publisher":"新潮社","pubdate":"2019-05-29","cover":"https://cover.openbd.jp/9784101331812.jpg","author":"佐藤優／著","description":"","price":"520","genre":"文庫","target":"一般","format":"文庫","content":"日本文学、評論、随筆、その他"}
,
{"isbn":"9784101362540","title":"サービスの達人たち おもてなしの神","volume":"","series":"新潮文庫","publisher":"新潮社","pubdate":"2019-05-29","cover":"https://cover.openbd.jp/9784101362540.jpg","author":"野地秩嘉／著","description":"","price":"520","genre":"文庫","target":"一般","format":"文庫","content":"日本文学、評論、随筆、その他"}
,
{"isbn":"9784101380636","title":"日の昇る国へ","volume":"","series":"新潮文庫","publisher":"新潮社","pubdate":"2019-05-29","cover":"https://cover.openbd.jp/9784101380636.jpg","author":"佐伯泰英／著","description":"","price":"670","genre":"文庫","target":"一般","format":"文庫","content":"日本文学、小説・物語"}
,
{"isbn":"9784101801544","title":"夢と魔法の国のリドル","volume":"","series":"新潮文庫","publisher":"新潮社","pubdate":"2019-05-29","cover":"https://cover.openbd.jp/9784101801544.jpg","author":"七河迦南／著","description":"","price":"670","genre":"文庫","target":"一般","format":"文庫","content":"日本文学、小説・物語"}
,
{"isbn":"9784101801551","title":"ＢＵＧ 広域警察極秘捜査班","volume":"","series":"新潮文庫","publisher":"新潮社","pubdate":"2019-05-29","cover":"https://cover.openbd.jp/9784101801551.jpg","author":"福田和代／著","description":"","price":"670","genre":"文庫","target":"一般","format":"文庫","content":"日本文学、小説・物語"}
,
{"isbn":"9784102472736","title":"イスラム最終戦争３","volume":"","series":"新潮文庫","publisher":"新潮社","pubdate":"2019-05-29","cover":"https://cover.openbd.jp/9784102472736.jpg","author":"マーク・グリーニー／著 田村源二／翻訳","description":"","price":"630","genre":"文庫","target":"一般","format":"文庫","content":"外国文学小説"}
,
{"isbn":"9784102472743","title":"イスラム最終戦争４","volume":"","series":"新潮文庫","publisher":"新潮社","pubdate":"2019-05-29","cover":"https://cover.openbd.jp/9784102472743.jpg","author":"マーク・グリーニー／著 田村源二／翻訳","description":"","price":"590","genre":"文庫","target":"一般","format":"文庫","content":"外国文学小説"}
,
{"isbn":"9784103041351","title":"ひよこ太陽","volume":"","series":"","publisher":"新潮社","pubdate":"2019-05-29","cover":"https://cover.openbd.jp/9784103041351.jpg","author":"田中慎弥／著","description":"今日も死ななかった、死なずに済んだ……。これは私小説なのか、それとも作家の妄想か？　不条理世界を生きる作家の待望の新作小説。","price":"1550","genre":"","target":"一般","format":"単行本","content":"日本文学、小説・物語"}
,
{"isbn":"9784103367352","title":"キュー","volume":"","series":"","publisher":"新潮社","pubdate":"2019-05-29","cover":"https://cover.openbd.jp/9784103367352.jpg","author":"上田岳弘／著","description":"僕の祖父はやがて世界そのものになる――超越系文学の旗手がその全才能を注ぎ、ウェブでの同時連載も話題となった、芥川賞受賞第一作","price":"2300","genre":"","target":"一般","format":"単行本","content":"日本文学、小説・物語"}
,
{"isbn":"9784103526315","title":"はい！ こちら子ども記者相談室デス！","volume":"","series":"","publisher":"新潮社","pubdate":"2019-05-29","cover":"https://cover.openbd.jp/9784103526315.jpg","author":"かめおか子ども新聞／著 ヨシタケシンスケ／イラスト","description":"「結婚できるのか」「息子にクソババアと言われた」。悩める大人へ、子ども記者の驚きの答えとは。ヨシタケシンスケのイラスト満載！","price":"1000","genre":"","target":"一般","format":"単行本","content":"日本文学、評論、随筆、その他"}
,
{"isbn":"9784103526414","title":"衰退産業でも稼げます","volume":"","series":"","publisher":"新潮社","pubdate":"2019-05-29","cover":"https://cover.openbd.jp/9784103526414.jpg","author":"藻谷ゆかり／著","description":"借金まみれの親の会社でも「代替わり」で蘇る！　ハーバードＭＢＡが革新に成功した商店・旅館・農業・伝統産業の事例を徹底研究。","price":"1500","genre":"","target":"一般","format":"単行本","content":"日本文学、評論、随筆、その他"}
,
{"isbn":"9784103526513","title":"僕とぼく","volume":"","series":"","publisher":"新潮社","pubdate":"2019-05-29","cover":"https://cover.openbd.jp/9784103526513.jpg","author":"川名壮志／著","description":"１５年前のあの日、妹の命が突然奪われた。被害者家族の兄弟を主人公に彼らが再び普通の幸福を取り戻すまでの感動ノンフィクション。","price":"1500","genre":"","target":"一般","format":"単行本","content":"日本文学、評論、随筆、その他"}
,
{"isbn":"9784104752157","title":"君たちが忘れてはいけないこと","volume":"","series":"","publisher":"新潮社","pubdate":"2019-05-29","cover":"https://cover.openbd.jp/9784104752157.jpg","author":"佐藤優／著","description":"資本主義の行方。後悔しない大学選び。教養って何だろう。高校生たちの切実な問題意識に真摯に応える名講義完全採録、待望の第二弾！","price":"1350","genre":"","target":"一般","format":"単行本","content":"日本文学、評論、随筆、その他"}
,
{"isbn":"9784105071110","title":"黒澤明の羅生門","volume":"","series":"","publisher":"新潮社","pubdate":"2019-05-29","cover":"https://cover.openbd.jp/9784105071110.jpg","author":"ポール・アンドラ／著 北村匡平／翻訳","description":"海外でまたクロサワが発見された。震災、廃墟、肉親の不慮の死、再生など世界的監督の真のメッセージを解き明かす映画評論の決定版。","price":"2500","genre":"","target":"一般","format":"単行本","content":"演劇・映画"}
,
{"isbn":"9784109101400","title":"翌檜","volume":"","series":"","publisher":"新潮社","pubdate":"2019-05-29","cover":"","author":"笙磨央／著","description":"","price":"1400","genre":"","target":"一般","format":"単行本","content":"日本文学、小説・物語"}
]
