[
{"isbn":"9784041081266","title":"ロード・エルメロイＩＩ世の事件簿　（４）","volume":"","series":"","publisher":"ＫＡＤＯＫＡＷＡ","pubdate":"2019-06-24","cover":"https://cover.openbd.jp/9784041081266.jpg","author":"東冬／著 三田誠／TYPE-MOON／原著 坂本みねぢ／企画 TENGEN／著","description":"新章【case.双貌塔イゼルマ】開幕！","price":"620","genre":"","target":"一般","format":"コミック","content":"コミックス・劇画"}
,
{"isbn":"9784041082355","title":"終末のノスフェラトゥ　（３）","volume":"","series":"","publisher":"ＫＡＤＯＫＡＷＡ","pubdate":"2019-06-24","cover":"https://cover.openbd.jp/9784041082355.jpg","author":"真じろう／著","description":"血に支配された宿命は呪いか…それとも…？【不死者の里篇】開幕!!","price":"620","genre":"","target":"一般","format":"コミック","content":"コミックス・劇画"}
,
{"isbn":"9784041083444","title":"機動戦士クロスボーン・ガンダム　DUST　（８）","volume":"","series":"","publisher":"ＫＡＤＯＫＡＷＡ","pubdate":"2019-06-24","cover":"https://cover.openbd.jp/9784041083444.jpg","author":"長谷川裕一／著 矢立肇・富野由悠季／原著 宮崎真一／著","description":"“王”が乱立する宇宙戦国時代の幕開け！","price":"620","genre":"","target":"一般","format":"コミック","content":"コミックス・劇画"}
,
{"isbn":"9784041083888","title":"春やきぬらん","volume":"","series":"","publisher":"ＫＡＤＯＫＡＷＡ","pubdate":"2019-06-24","cover":"https://cover.openbd.jp/9784041083888.jpg","author":"杉本亜未／著","description":"書生×画学生×教授。美を巡る明治時代の三角関係。","price":"1500","genre":"","target":"一般","format":"コミック","content":"コミックス・劇画"}
,
{"isbn":"9784041083895","title":"天照様ご乱心","volume":"","series":"","publisher":"ＫＡＤＯＫＡＷＡ","pubdate":"2019-06-24","cover":"https://cover.openbd.jp/9784041083895.jpg","author":"キリエ／著","description":"女神も、ときには恋をする。いにしえ＆とこしえラブコメディ！","price":"620","genre":"","target":"一般","format":"コミック","content":"コミックス・劇画"}
,
{"isbn":"9784041083918","title":"四ノ宮くんには理由がある　（２）","volume":"","series":"","publisher":"ＫＡＤＯＫＡＷＡ","pubdate":"2019-06-24","cover":"https://cover.openbd.jp/9784041083918.jpg","author":"小田切ほたる／著","description":"四ノ宮家三男の雨京には「超能力」のほかにもワケがあり―――！？","price":"620","genre":"","target":"一般","format":"コミック","content":"コミックス・劇画"}
,
{"isbn":"9784048842303","title":"歌集　雪ふれば雪　花咲けば花","volume":"","series":"","publisher":"角川文化振興財団","pubdate":"2019-06-24","cover":"https://cover.openbd.jp/9784048842303.jpg","author":"山田純華／著","description":"原発事故で美しい故郷を失っても、季節は誰にも等しく訪れる","price":"2800","genre":"","target":"一般","format":"単行本","content":"日本文学詩歌"}
,
{"isbn":"9784049126136","title":"魔法のiらんどCOMICS お女ヤン!! イケメン☆ヤンキー☆パラダイス（１３）","volume":"","series":"","publisher":"ＫＡＤＯＫＡＷＡ","pubdate":"2019-06-24","cover":"https://cover.openbd.jp/9784049126136.jpg","author":"貴里みち／著 岬／原著","description":"シリーズ累計70万部突破!!妄想ラブが爆発、大人気コミックス第13巻！","price":"580","genre":"","target":"一般","format":"コミック","content":"コミックス・劇画"}
,
{"isbn":"9784049127218","title":"軌跡シリーズ15周年記念 閃の軌跡キャラクターマニアクス","volume":"","series":"","publisher":"ＫＡＤＯＫＡＷＡ","pubdate":"2019-06-24","cover":"https://cover.openbd.jp/9784049127218.jpg","author":"電撃ＰｌａｙＳｔａｔｉｏｎ編集部／編集","description":"軌跡シリーズ15周年記念、閃の軌跡キャラのすべてがこの１冊に！","price":"4500","genre":"","target":"一般","format":"単行本","content":"諸芸・娯楽"}
,
{"isbn":"9784065148211","title":"令和の日本革命　2030年の日本はこうなる","volume":"","series":"","publisher":"講談社","pubdate":"2019-06-24","cover":"https://cover.openbd.jp/9784065148211.jpg","author":"田原総一朗／著","description":"当代随一のジャーナリストが令和の日本に見出した「新ＹＫＫ」小泉進次郎、村井英樹、小林史明、福田達夫―気鋭の政治家が描く国家像","price":"1200","genre":"","target":"一般","format":"単行本","content":"社会"}
,
{"isbn":"9784065169148","title":"週刊現代別冊　おとなの週刊現代　2019　vol．3　もっと知りたい死後の手続き","volume":"","series":"","publisher":"講談社","pubdate":"2019-06-24","cover":"https://cover.openbd.jp/9784065169148.jpg","author":"週刊現代／編集","description":"２７万部突破の「おとなの週刊現代　死後の手続きはこんなに大変です」の第２弾。２０１９年７月１日からの相続法改正にも完全対応。","price":"907","genre":"","target":"雑誌扱い","format":"ムック・その他","content":"総記"}
,
{"isbn":"9784073408079","title":"ＣＯＭＩＣ魂　別冊　子連れ狼　どさ御用編","volume":"","series":"","publisher":"主婦の友社","pubdate":"2019-06-24","cover":"","author":"小池一夫／企画 小島剛夕／イラスト","description":"日本が誇る不朽の名作・第8号。一族の無念を晴らすべく刺客道を行く拝一刀・大五郎父子。その運命は…？　時代劇漫画の金字塔！","price":"593","genre":"","target":"雑誌扱い","format":"ムック・その他","content":"コミックス・劇画"}
]
