[
{"isbn":"9784003279915","title":"ラテンアメリカ民話集","volume":"","series":"","publisher":"岩波書店","pubdate":"2019-12-15","cover":"https://cover.openbd.jp/9784003279915.jpg","author":"三原幸久／編集","description":"ラテンアメリカに広く分布するもの，日本の昔話に関係がありそうなものを中心に37話を精選．","price":"920","genre":"文庫","target":"一般","format":"文庫","content":"外国文学、その他"}
,
{"isbn":"9784003600375","title":"子規紀行文集","volume":"","series":"","publisher":"岩波書店","pubdate":"2019-12-15","cover":"https://cover.openbd.jp/9784003600375.jpg","author":"復本一郎／編集","description":"近代俳句を立ち上げた文豪子規（1867-1902）の代表的な紀行文8篇を精選して，詳細な注解を付した．","price":"740","genre":"文庫","target":"一般","format":"文庫","content":"日本文学詩歌"}
,
{"isbn":"9784003750902","title":"サラムボー　（下）","volume":"","series":"","publisher":"岩波書店","pubdate":"2019-12-15","cover":"https://cover.openbd.jp/9784003750902.jpg","author":"フローベール／著 中條屋進／翻訳","description":"反乱軍のリーダーと，国を守る神官との許されぬ恋．激情と官能と宿命が導く古代オリエントの緋色の世界．（全二冊）","price":"840","genre":"文庫","target":"一般","format":"文庫","content":"外国文学小説"}
,
{"isbn":"9784006004125","title":"「鎖国」を見直す","volume":"","series":"","publisher":"岩波書店","pubdate":"2019-12-15","cover":"https://cover.openbd.jp/9784006004125.jpg","author":"荒野泰典／著","description":"江戸時代の日本は「鎖国」ではなかった――著者の提唱する「海禁・華夷秩序論」のエッセンスをまとめる．","price":"880","genre":"文庫","target":"一般","format":"文庫","content":"日本歴史"}
,
{"isbn":"9784006023140","title":"黒雲の下で卵をあたためる","volume":"","series":"","publisher":"岩波書店","pubdate":"2019-12-15","cover":"https://cover.openbd.jp/9784006023140.jpg","author":"小池昌代／著","description":"詩人は詩をどのように読み，文字を観て，何を感じるのか．解説，片岡義男．","price":"920","genre":"文庫","target":"一般","format":"文庫","content":"日本文学、評論、随筆、その他"}
,
{"isbn":"9784006033170","title":"全盲の弁護士 竹下義樹","volume":"","series":"","publisher":"岩波書店","pubdate":"2019-12-15","cover":"https://cover.openbd.jp/9784006033170.jpg","author":"小林照幸／著","description":"視覚障害をものともせず九度目の挑戦で夢をつかんだ男，竹下義樹．読む人の心を揺さぶる痛快ノンフィクション！","price":"1220","genre":"文庫","target":"一般","format":"文庫","content":"日本文学、評論、随筆、その他"}
,
{"isbn":"9784047358607","title":"不本意ですが、竜騎士団が過保護です ３","volume":"","series":"","publisher":"ＫＡＤＯＫＡＷＡ","pubdate":"2019-12-15","cover":"https://cover.openbd.jp/9784047358607.jpg","author":"乙川れい／著 くまの柚子／イラスト","description":"潜入王女、ついに身バレ!?　引き離される二人の恋の行方は――!?","price":"660","genre":"","target":"一般","format":"文庫","content":"日本文学、小説・物語"}
,
{"isbn":"9784047358621","title":"乙女ゲームの世界で私が悪役令嬢!?　そんなのお断りです！","volume":"","series":"","publisher":"ＫＡＤＯＫＡＷＡ","pubdate":"2019-12-15","cover":"https://cover.openbd.jp/9784047358621.jpg","author":"蒼月／著 笹原亜美／イラスト","description":"恋愛フラグ折るはずが…溺愛フラグ乱立!?　怒涛の逆ハーラブコメ開幕♪","price":"680","genre":"","target":"一般","format":"文庫","content":"日本文学、小説・物語"}
,
{"isbn":"9784065164990","title":"タッチ＆トーキング／ミニオン　おしゃべりボブ","volume":"","series":"","publisher":"講談社","pubdate":"2019-12-15","cover":"https://cover.openbd.jp/9784065164990.jpg","author":"講談社／編集","description":"ミニオンの中で一番の人気者「ボブ」。頭やお腹をさわるとボブが笑ったり、話しかけると答えてくれるユニークなおもちゃです！","price":"2300","genre":"","target":"一般","format":"単行本","content":"諸芸・娯楽"}
,
{"isbn":"9784065169476","title":"現役歯科医が警鐘　こんな歯医者に行ってはいけない","volume":"","series":"","publisher":"講談社ビーシー","pubdate":"2019-12-15","cover":"https://cover.openbd.jp/9784065169476.jpg","author":"今枝誠二／著","description":"まだ間に合う！歯科医に勝手に削られ抜かれ歯を失う前に、口腔内ケアを怠って病気になる前に、知っておきたい最新歯科学の真実とは？","price":"1000","genre":"","target":"一般","format":"単行本","content":"医学・歯学・薬学"}
,
{"isbn":"9784163911458","title":"心と体のもやもやがスーッと消える食事術","volume":"","series":"","publisher":"文藝春秋","pubdate":"2019-12-15","cover":"https://cover.openbd.jp/9784163911458.jpg","author":"工藤孝文／著","description":"頭イタイタ型、肩ガチガチ・首ロック型……6タイプ別食事法で「病名のつかない」もやもや不調が大きく改善。感動の食事法決定版！","price":"1300","genre":"","target":"一般","format":"単行本","content":"家事"}
]
