{"2020-01-26":[{"isbn":"9784000050616","title":"ビジュアル　医学全史","pubdate":"2020-01-26","cover":"https://cover.openbd.jp/9784000050616.jpg"},{"isbn":"9784000613842","title":"私にとっての介護","pubdate":"2020-01-26","cover":"https://cover.openbd.jp/9784000613842.jpg"}],"2020-01-31":[{"isbn":"9784000229692","title":"孤塁　双葉郡消防士たちの3.11","pubdate":"2020-01-31","cover":"https://cover.openbd.jp/9784000229692.jpg"},{"isbn":"9784000928472","title":"別冊　（下）","pubdate":"2020-01-31","cover":"https://cover.openbd.jp/9784000928472.jpg"}],"2020-01-30":[{"isbn":"9784000237420","title":"それを，真の名で呼ぶならば","pubdate":"2020-01-30","cover":"https://cover.openbd.jp/9784000237420.jpg"},{"isbn":"9784000245425","title":"人殺しの花","pubdate":"2020-01-30","cover":"https://cover.openbd.jp/9784000245425.jpg"}],"2020-02-09":[{"isbn":"9784000240604","title":"点・線・面","pubdate":"2020-02-09","cover":"https://cover.openbd.jp/9784000240604.jpg"},{"isbn":"9784000296922","title":"知りたい！ ネコごころ","pubdate":"2020-02-09","cover":"https://cover.openbd.jp/9784000296922.jpg"}],"2020-01-24":[{"isbn":"9784000296915","title":"フラクタル","pubdate":"2020-01-24","cover":"https://cover.openbd.jp/9784000296915.jpg"},{"isbn":"9784040641959","title":"―異能―","pubdate":"2020-01-24","cover":"https://cover.openbd.jp/9784040641959.jpg"}],"2020-02-15":[{"isbn":"9784000613880","title":"黄犬交遊抄","pubdate":"2020-02-15","cover":"https://cover.openbd.jp/9784000613880.jpg"},{"isbn":"9784040644554","title":"ブラザー・トラップ　4","pubdate":"2020-02-15","cover":"https://cover.openbd.jp/9784040644554.jpg"}],"2020-02-07":[{"isbn":"9784001126884","title":"プレストとゼスト　リンボランドをいく","pubdate":"2020-02-07","cover":"https://cover.openbd.jp/9784001126884.jpg"},{"isbn":"9784002710181","title":"ボランティアってなんだっけ？","pubdate":"2020-02-07","cover":"https://cover.openbd.jp/9784002710181.jpg"}],"2020-02-16":[{"isbn":"9784001146219","title":"ベルリン1919　赤い水兵（上）","pubdate":"2020-02-16","cover":"https://cover.openbd.jp/9784001146219.jpg"},{"isbn":"9784001146226","title":"ベルリン1919　赤い水兵（下）","pubdate":"2020-02-16","cover":"https://cover.openbd.jp/9784001146226.jpg"}],"2020-01-23":[{"isbn":"9784004318057","title":"江南の発展 南宋まで","pubdate":"2020-01-23","cover":"https://cover.openbd.jp/9784004318057.jpg"},{"isbn":"9784004318217","title":"日本思想史","pubdate":"2020-01-23","cover":"https://cover.openbd.jp/9784004318217.jpg"}],"2020-02-17":[{"isbn":"9784010112946","title":"学校では教えてくれない大切なこと（29）ＡＩって何だろう？－人工知能が拓く世界－","pubdate":"2020-02-17","cover":"https://cover.openbd.jp/9784010112946.jpg"},{"isbn":"9784010113370","title":"学校では教えてくれない大切なこと（28）日本のこと－伝統・文化・風習－","pubdate":"2020-02-17","cover":"https://cover.openbd.jp/9784010113370.jpg"}],"2020-02-06":[{"isbn":"9784010347010","title":"共通テスト地理B集中講義","pubdate":"2020-02-06","cover":"https://cover.openbd.jp/9784010347010.jpg"},{"isbn":"9784010347027","title":"日本史基礎問題精講","pubdate":"2020-02-06","cover":"https://cover.openbd.jp/9784010347027.jpg"}],"2020-01-21":[{"isbn":"9784022216205","title":"朝日新聞報道写真集２０２０","pubdate":"2020-01-21","cover":"https://cover.openbd.jp/9784022216205.jpg"},{"isbn":"9784041085066","title":"どうせ24時間 印象に残る女になれ","pubdate":"2020-01-21","cover":"https://cover.openbd.jp/9784041085066.jpg"}],"2020-02-10":[{"isbn":"9784022630933","title":"ベトナム戦争と私　カメラマンの記録した戦場","pubdate":"2020-02-10","cover":"https://cover.openbd.jp/9784022630933.jpg"},{"isbn":"9784022630940","title":"アフリカからアジアへ　現生人類はどう拡散したか","pubdate":"2020-02-10","cover":"https://cover.openbd.jp/9784022630940.jpg"}],"2020-02-05":[{"isbn":"9784033327501","title":"おなまえ100","pubdate":"2020-02-05","cover":"https://cover.openbd.jp/9784033327501.jpg"},{"isbn":"9784035398400","title":"さらに、物語は迷いこむ","pubdate":"2020-02-05","cover":"https://cover.openbd.jp/9784035398400.jpg"}],"2020-02-12":[{"isbn":"9784033484907","title":"こんな おおきな かず、みたこと ある？","pubdate":"2020-02-12","cover":"https://cover.openbd.jp/9784033484907.jpg"},{"isbn":"9784034395400","title":"うりぼうウリタ もりのがっこう","pubdate":"2020-02-12","cover":"https://cover.openbd.jp/9784034395400.jpg"}],"2020-01-29":[{"isbn":"9784035445203","title":"平和と人権解放につくした人たち","pubdate":"2020-01-29","cover":"https://cover.openbd.jp/9784035445203.jpg"},{"isbn":"9784037272302","title":"グレーテルの白い小鳥","pubdate":"2020-01-29","cover":"https://cover.openbd.jp/9784037272302.jpg"}],"2020-01-27":[{"isbn":"9784040642871","title":"今日どこさん行くと？３","pubdate":"2020-01-27","cover":"https://cover.openbd.jp/9784040642871.jpg"},{"isbn":"9784040642888","title":"百合ドリル　自由研究編","pubdate":"2020-01-27","cover":"https://cover.openbd.jp/9784040642888.jpg"}],"2020-02-14":[{"isbn":"9784040643168","title":"つんのいちぞく","pubdate":"2020-02-14","cover":"https://cover.openbd.jp/9784040643168.jpg"},{"isbn":"9784040643182","title":"おかあさんライフ。","pubdate":"2020-02-14","cover":"https://cover.openbd.jp/9784040643182.jpg"}],"2020-02-01":[{"isbn":"9784040643885","title":"「好きだけど付き合えない。」ってなんなの？「アイスコーヒーをホットで！」って頼むの？","pubdate":"2020-02-01","cover":"https://cover.openbd.jp/9784040643885.jpg"},{"isbn":"9784041082591","title":"真の仲間じゃないと勇者のパーティーを追い出されたので、辺境でスローライフすることにしました6","pubdate":"2020-02-01","cover":"https://cover.openbd.jp/9784041082591.jpg"}],"2020-02-08":[{"isbn":"9784040822570","title":"イスラエルとユダヤ人 考察ノート","pubdate":"2020-02-08","cover":"https://cover.openbd.jp/9784040822570.jpg"},{"isbn":"9784040823164","title":"探偵の現場","pubdate":"2020-02-08","cover":"https://cover.openbd.jp/9784040823164.jpg"}],"2020-02-04":[{"isbn":"9784041080177","title":"賢者の孫　Ｅｘｔｒａ　Ｓｔｏｒｙ　（２）","pubdate":"2020-02-04","cover":"https://cover.openbd.jp/9784041080177.jpg"},{"isbn":"9784041081235","title":"賢者の孫　（１３）","pubdate":"2020-02-04","cover":"https://cover.openbd.jp/9784041081235.jpg"}],"2020-02-13":[{"isbn":"9784041081860","title":"小説　野性時代　第１９６号　２０２０年３月号","pubdate":"2020-02-13","cover":"https://cover.openbd.jp/9784041081860.jpg"},{"isbn":"9784093523844","title":"私生活","pubdate":"2020-02-13","cover":"https://cover.openbd.jp/9784093523844.jpg"}],"2020-01-28":[{"isbn":"9784041090732","title":"その境界を越えてゆけ","pubdate":"2020-01-28","cover":"https://cover.openbd.jp/9784041090732.jpg"},{"isbn":"9784130263504","title":"歴史に向きあう","pubdate":"2020-01-28","cover":"https://cover.openbd.jp/9784130263504.jpg"}],"2020-02-03":[{"isbn":"9784048966498","title":"和田颯 1st写真集　25","pubdate":"2020-02-03","cover":"https://cover.openbd.jp/9784048966498.jpg"},{"isbn":"9784048966603","title":"【改訂版】LUNA SEA COMPLETE WORKS PERFECT DISCOGRAPHY 30TH ANNIVERSARY","pubdate":"2020-02-03","cover":"https://cover.openbd.jp/9784048966603.jpg"}],"2020-01-22":[{"isbn":"9784048966511","title":"北川尚弥 Photo&DVD　Booｋ［ish］","pubdate":"2020-01-22","cover":"https://cover.openbd.jp/9784048966511.jpg"},{"isbn":"9784049129786","title":"いいんちょと不良くん1","pubdate":"2020-01-22","cover":"https://cover.openbd.jp/9784049129786.jpg"}],"2020-02-02":[{"isbn":"9784065179147","title":"特製オリジナル枕つき　安眠ウエーブ枕　「極上」","pubdate":"2020-02-02","cover":"https://cover.openbd.jp/9784065179147.jpg"}],"2020-01-25":[{"isbn":"9784284204583","title":"もう投げださない！  続けるチカラ","pubdate":"2020-01-25","cover":"https://cover.openbd.jp/9784284204583.jpg"},{"isbn":"9784297110260","title":"バリュー投資家のための「米国株」データ分析―ひと握りの優良株が割安になるときの見分け方","pubdate":"2020-01-25","cover":"https://cover.openbd.jp/9784297110260.jpg"}]}